{
  "schema_version": "articlestory.v1",
  "doi": "10.2196/preprints.37324",
  "title": "Establishing Institutional Scores With the Rigor and Transparency Index: Large-scale Analysis of Scientific Reporting Quality (Preprint)",
  "authors": [
    {
      "name": "Joseph Menke",
      "orcid": "0000-0002-7374-7549",
      "affiliation": "University of California San Diego"
    },
    {
      "name": "Peter Eckmann",
      "orcid": "0000-0002-5388-9451",
      "affiliation": "University of California San Diego"
    },
    {
      "name": "\u0130brahim Burak \u00d6zyurt",
      "orcid": "0000-0003-3944-1893",
      "affiliation": "University of California San Diego"
    },
    {
      "name": "Martijn Roelandse",
      "orcid": "0000-0001-5596-8084",
      "affiliation": null
    },
    {
      "name": "Nathan Anderson",
      "orcid": "0000-0001-5408-5095",
      "affiliation": null
    },
    {
      "name": "Jeffrey S. Grethe",
      "orcid": "0000-0001-5212-7052",
      "affiliation": "University of California San Diego"
    },
    {
      "name": "Anthony Gamst",
      "orcid": "0000-0002-6811-7649",
      "affiliation": "University of California San Diego"
    },
    {
      "name": "Anita Bandrowski",
      "orcid": "0000-0002-5497-0243",
      "affiliation": "University of California San Diego"
    }
  ],
  "work_type": "preprint",
  "work_stage": "unknown",
  "venue": {
    "name": "Unknown",
    "publisher": null,
    "issn_l": null,
    "issn": [],
    "url": null
  },
  "bibliographic": {
    "published_year": null,
    "published_date": null,
    "volume": null,
    "issue": null,
    "pages": null
  },
  "abstract": null,
  "language": null,
  "identifiers": {
    "doi": "10.2196/preprints.37324",
    "openalex_id": "https://openalex.org/W4213336392",
    "pub_year": 2022
  },
  "graph": {},
  "signals": {
    "template_authors": [
      {
        "name": "Joseph Menke",
        "orcid": "0000-0002-7374-7549",
        "affiliation": "University of California San Diego",
        "affiliation_url": "https://ror.org/0168r3w48",
        "is_corresponding": false
      },
      {
        "name": "Peter Eckmann",
        "orcid": "0000-0002-5388-9451",
        "affiliation": "University of California San Diego",
        "affiliation_url": "https://ror.org/0168r3w48",
        "is_corresponding": false
      },
      {
        "name": "\u0130brahim Burak \u00d6zyurt",
        "orcid": "0000-0003-3944-1893",
        "affiliation": "University of California San Diego",
        "affiliation_url": "https://ror.org/0168r3w48",
        "is_corresponding": false
      },
      {
        "name": "Martijn Roelandse",
        "orcid": "0000-0001-5596-8084",
        "affiliation": null,
        "affiliation_url": null,
        "is_corresponding": false
      },
      {
        "name": "Nathan Anderson",
        "orcid": "0000-0001-5408-5095",
        "affiliation": null,
        "affiliation_url": null,
        "is_corresponding": false
      },
      {
        "name": "Jeffrey S. Grethe",
        "orcid": "0000-0001-5212-7052",
        "affiliation": "University of California San Diego",
        "affiliation_url": "https://ror.org/0168r3w48",
        "is_corresponding": false
      },
      {
        "name": "Anthony Gamst",
        "orcid": "0000-0002-6811-7649",
        "affiliation": "University of California San Diego",
        "affiliation_url": "https://ror.org/0168r3w48",
        "is_corresponding": false
      },
      {
        "name": "Anita Bandrowski",
        "orcid": "0000-0002-5497-0243",
        "affiliation": "University of California San Diego",
        "affiliation_url": "https://ror.org/0168r3w48",
        "is_corresponding": true
      }
    ],
    "raw_events": {
      "total": 0,
      "by_source": [],
      "examples": []
    },
    "attention_summary": {
      "total_mentions": 9
    },
    "citing_landscape": {
      "total_citing_works": 25,
      "citations_by_year": [],
      "top_venues": [],
      "work_types": [],
      "top_concepts": [],
      "countries": [],
      "sectors": [],
      "top_institutions": [],
      "top_authors": [],
      "inst_concentration": 0,
      "median_cites": 0,
      "captured_citing_works": 0
    },
    "citation_count": 25,
    "percentiles": {
      "value": 0.02274405,
      "is_in_top_1_percent": false,
      "is_in_top_10_percent": false
    },
    "rrids": {
      "europepmc": {
        "ok": false,
        "reason": "not_found",
        "doi": "10.2196/preprints.37324",
        "rrids": [],
        "items": [],
        "count": 0
      }
    },
    "stewardship": {
      "data_links": [],
      "clinical_trials": [],
      "funding": []
    },
    "funding": [],
    "contributors": {
      "source": "openalex",
      "authors": [
        {
          "name": "Joseph Menke",
          "openalex_author_id": null,
          "orcid": "0000-0002-7374-7549",
          "position": null,
          "is_corresponding": null,
          "institutions": [
            {
              "name": "University of California San Diego",
              "openalex_institution_id": null,
              "ror": null,
              "country_code": null,
              "type": null
            }
          ]
        },
        {
          "name": "Peter Eckmann",
          "openalex_author_id": null,
          "orcid": "0000-0002-5388-9451",
          "position": null,
          "is_corresponding": null,
          "institutions": [
            {
              "name": "University of California San Diego",
              "openalex_institution_id": null,
              "ror": null,
              "country_code": null,
              "type": null
            }
          ]
        },
        {
          "name": "\u0130brahim Burak \u00d6zyurt",
          "openalex_author_id": null,
          "orcid": "0000-0003-3944-1893",
          "position": null,
          "is_corresponding": null,
          "institutions": [
            {
              "name": "University of California San Diego",
              "openalex_institution_id": null,
              "ror": null,
              "country_code": null,
              "type": null
            }
          ]
        },
        {
          "name": "Martijn Roelandse",
          "openalex_author_id": null,
          "orcid": "0000-0001-5596-8084",
          "position": null,
          "is_corresponding": null,
          "institutions": []
        },
        {
          "name": "Nathan Anderson",
          "openalex_author_id": null,
          "orcid": "0000-0001-5408-5095",
          "position": null,
          "is_corresponding": null,
          "institutions": []
        },
        {
          "name": "Jeffrey S. Grethe",
          "openalex_author_id": null,
          "orcid": "0000-0001-5212-7052",
          "position": null,
          "is_corresponding": null,
          "institutions": [
            {
              "name": "University of California San Diego",
              "openalex_institution_id": null,
              "ror": null,
              "country_code": null,
              "type": null
            }
          ]
        },
        {
          "name": "Anthony Gamst",
          "openalex_author_id": null,
          "orcid": "0000-0002-6811-7649",
          "position": null,
          "is_corresponding": null,
          "institutions": [
            {
              "name": "University of California San Diego",
              "openalex_institution_id": null,
              "ror": null,
              "country_code": null,
              "type": null
            }
          ]
        },
        {
          "name": "Anita Bandrowski",
          "openalex_author_id": null,
          "orcid": "0000-0002-5497-0243",
          "position": null,
          "is_corresponding": null,
          "institutions": [
            {
              "name": "University of California San Diego",
              "openalex_institution_id": null,
              "ror": null,
              "country_code": null,
              "type": null
            }
          ]
        }
      ],
      "institutions": [
        {
          "name": "University of California San Diego",
          "openalex_institution_id": null,
          "ror": null,
          "country_code": null,
          "type": null
        }
      ],
      "warnings": []
    },
    "concepts": [
      {
        "display_name": "Transparency (behavior)",
        "score": 0.75
      },
      {
        "display_name": "Checklist",
        "score": 0.58
      },
      {
        "display_name": "Rigour",
        "score": 0.56
      },
      {
        "display_name": "Computer science",
        "score": 0.41
      },
      {
        "display_name": "Library science",
        "score": 0.4
      },
      {
        "display_name": "Accounting",
        "score": 0.38
      },
      {
        "display_name": "Medicine",
        "score": 0.35
      },
      {
        "display_name": "Political science",
        "score": 0.32
      },
      {
        "display_name": "Psychology",
        "score": 0.29
      },
      {
        "display_name": "Law",
        "score": 0.17
      },
      {
        "display_name": "Mathematics",
        "score": 0.13
      },
      {
        "display_name": "Business",
        "score": 0.11
      },
      {
        "display_name": "Cognitive psychology",
        "score": 0.09
      },
      {
        "display_name": "Geometry",
        "score": 0.0
      }
    ],
    "teaching_adoption": {
      "ocw": [],
      "holdings": {
        "worldcat_url": "https://www.worldcat.org/search?q=ti:Establishing%20Institutional%20Scores%20With%20the%20Rigor%20and%20Transparency%20Index%3A%20Large-scale%20Analysis%20of%20Scientific%20Reporting%20Quality%20%28Preprint%29",
        "library_subjects": [],
        "ol_holdings": 0
      }
    },
    "published_metrics": {
      "doi": "10.2196/37324",
      "citations": 25,
      "events": 9
    },
    "reuse_graph": {
      "uses_data": [],
      "reused_by_count": 25,
      "reused_by_breakdown": {},
      "reused_by_links": []
    },
    "social_mentions": {},
    "risk_layer": {
      "is_retracted": false,
      "expression_of_concern": false,
      "pubpeer_threads": 0,
      "pubpeer_url": null
    }
  },
  "roles": [
    {
      "id": "scholarly_uptake",
      "label": "Scholarly uptake",
      "strength": 0.3,
      "evidence": {
        "total": 25
      }
    }
  ],
  "claims": [],
  "concepts": [],
  "primary_concept": null,
  "impact": {
    "citations": [],
    "scite": {
      "total": 1,
      "supporting": 0,
      "mentioning": 1,
      "contradicting": 0,
      "last_updated": null,
      "source_url": "https://scite.ai/reports/10.2196/preprints.37324"
    },
    "events": {
      "total": 0,
      "by_source": [],
      "examples": []
    },
    "downloads": {}
  },
  "access": {
    "landing_page_url": "https://doi.org/10.2196/preprints.37324",
    "oa_status": "gold",
    "is_oa": true,
    "best_oa_location": {
      "url": "https://doi.org/10.2196/preprints.37324",
      "pdf_url": null,
      "is_best": true
    },
    "other_locations": [],
    "license": {
      "spdx": "cc-by",
      "source": "openalex"
    }
  },
  "citations": {
    "citation_count": 25,
    "referenced_works_count": null,
    "trajectory": []
  },
  "attention": {
    "event_count": 0,
    "sources_breakdown": {},
    "notable_events": []
  },
  "scite": null,
  "benchmarks": null,
  "relations": {
    "published_version_doi": null,
    "preprint_version_doi": null,
    "related_dois": [],
    "relation_source": null
  },
  "narrative": "<h3 class=\"story-subheading\">Short impact summary</h3>\n<p class=\"story-text\">This article presents the results of a large-scale analysis established by the Rigor and Transparency Index, highlighting the quality of scientific reporting. With 25 citations, it demonstrates significant reach and implications within the scholarly community.</p>\n<h3 class=\"story-subheading\">Full narrative</h3>\n<p class=\"story-text\">The study, authored by Joseph Menke, Peter Eckmann, \u0130brahim Burak \u00d6zyurt, Martijn Roelandse, Nathan Anderson, and colleagues, effectively employs the Rigor and Transparency Index to analyze the quality of scientific reporting across disciplines. As a preprint that has subsequently been published, it shows a combined impact evidenced by both its preprint and published version citation count of 25. This reflects a growing recognition of the importance of transparency and rigor in scientific research.</p>\n<p class=\"story-text\">The findings from this analysis provide critical insights into best practices for scientific reporting, thereby setting a standard for future publications in the field. The authors\u2019 collaboration among key institutions like the University of California San Diego enhances the credibility and reach of this work, making it a vital contribution to ongoing debates in stem disciplines.</p>\n<p class=\"story-text\">While there are no notable online community discussions related to the work, its academic citations indicate a solid foundation among researchers, suggesting that the analysis has sparked interest in improving the standards of scientific disclosures. The absence of funding agencies suggests an independent investigation, potentially pointing to a broader engagement with institutional priorities in research integrity.</p>\n<p class=\"story-text\">Importantly, this work's emphasis on quality reporting serves not just as a scholarly contribution but as a rallying call for enhanced methodological transparency in scientific investigations. This aligns with the current demands for improving reproducibility across various research landscapes, further underscoring the relevance of this preprint in shaping future research endeavors.</p>",
  "provenance": {},
  "story_type": "ArticleStory"
}