{
  "book_id": "10.11116/9789461664518",
  "title": "Plutarch\u2019s Cosmological Ethics",
  "authors": [
    "Bram Demulder"
  ],
  "publisher": "Leuven University Press",
  "publication_year": 2022,
  "identifiers": {
    "discipline": "humanities"
  },
  "doab": {},
  "abstract": null,
  "hosts": [],
  "citations": [],
  "concepts": [],
  "signals": {
    "template_authors": [
      {
        "name": "Bram Demulder",
        "orcid": "0000-0002-0469-8974",
        "affiliation": null,
        "affiliation_url": null,
        "is_corresponding": true
      }
    ],
    "series_metadata": {
      "series_name": null,
      "series_id": null,
      "series_issn": null,
      "belongs_to_series": false
    },
    "citation_count": 1,
    "percentiles": {
      "value": 0.75589675,
      "is_in_top_1_percent": false,
      "is_in_top_10_percent": false
    },
    "citing_landscape": {
      "total_citing_works": 1,
      "citations_by_year": [
        {
          "year": 2024,
          "count": 1
        }
      ],
      "top_venues": [
        {
          "label": "Peitho Examina Antiqua",
          "count": 1
        }
      ],
      "work_types": [
        {
          "label": "article",
          "count": 1
        }
      ],
      "top_concepts": [
        {
          "label": "Mouthpiece",
          "count": 1
        },
        {
          "label": "Aeronautics",
          "count": 1
        },
        {
          "label": "Psychology",
          "count": 1
        }
      ],
      "countries": [],
      "sectors": [],
      "top_institutions": [],
      "top_authors": [
        {
          "label": "David J. Murphy",
          "url": "https://openalex.org/A5112426257",
          "badge": "Profile",
          "count": 1
        }
      ],
      "inst_concentration": 0.0,
      "median_cites": 0.0
    },
    "book_reviews": {
      "review_count": 0,
      "top_reviews": []
    },
    "library_and_syllabi": {
      "worldcat_url": "https://www.worldcat.org/search?q=bn:9789461664518",
      "library_subjects": [],
      "ol_holdings": 0
    },
    "volume_footprint": {
      "is_edited_volume": true,
      "chapter_count": 1,
      "total_chapter_citations": 0,
      "network_size": 0,
      "core_network_authors": []
    },
    "contributors": {
      "source": "openalex",
      "authors": [
        {
          "name": "Bram Demulder",
          "openalex_author_id": null,
          "orcid": "0000-0002-0469-8974",
          "position": null,
          "is_corresponding": null,
          "institutions": []
        }
      ],
      "institutions": [],
      "warnings": []
    },
    "rrids": {
      "europepmc": {
        "count": 0,
        "items": []
      }
    },
    "raw_events": {
      "total": 1,
      "by_source": [
        [
          "crossref",
          1
        ]
      ],
      "examples": [
        {
          "source_id": "crossref",
          "relation_type": "is-identical-to",
          "url": "https://doi.org/10.2307/j.ctv2p5zwnh",
          "title": "https://doi.org/10.2307/j.ctv2p5zwnh",
          "occurred_at": "2022-06-23"
        }
      ],
      "first_seen": "2022-06-23",
      "last_seen": "2022-06-23"
    },
    "attention_summary": {
      "total_mentions": 1,
      "web_mentions": 0,
      "web_mentions_breakdown": {
        "substack": 0,
        "blog": 0,
        "podcast": 0
      }
    },
    "data_citations": {
      "datasets_cited": [],
      "cited_as_dataset": [],
      "total": 0,
      "endpoint": "crossref-data-citations"
    },
    "concepts": [
      {
        "display_name": "Tranquillity",
        "score": 0.77
      },
      {
        "display_name": "Interpretation (philosophy)",
        "score": 0.7
      },
      {
        "display_name": "Cosmology",
        "score": 0.69
      },
      {
        "display_name": "Philosophy",
        "score": 0.52
      },
      {
        "display_name": "Foundation (evidence)",
        "score": 0.49
      },
      {
        "display_name": "Epistemology",
        "score": 0.41
      },
      {
        "display_name": "Law",
        "score": 0.19
      },
      {
        "display_name": "Psychology",
        "score": 0.17
      },
      {
        "display_name": "Physics",
        "score": 0.13
      },
      {
        "display_name": "Astronomy",
        "score": 0.09
      },
      {
        "display_name": "Political science",
        "score": 0.09
      },
      {
        "display_name": "Linguistics",
        "score": 0.06
      },
      {
        "display_name": "Neuroscience",
        "score": 0.0
      }
    ],
    "sdgs": [
      {
        "display_name": "Peace, Justice and strong institutions",
        "score": 0.44
      }
    ],
    "is_oa": true,
    "oa_status": "hybrid",
    "oa_url": "https://doi.org/10.11116/9789461664518",
    "teaching_adoption": {
      "ocw": [],
      "youtube": [],
      "holdings": {
        "worldcat_url": "https://www.worldcat.org/search?q=bn:9789461664518",
        "library_subjects": [],
        "ol_holdings": 0
      },
      "otl": {}
    },
    "stewardship": {
      "data_links": [],
      "clinical_trials": [],
      "funding": []
    },
    "funding": [
      {
        "funder": "KU Leuven",
        "award": "Thoth Verified"
      }
    ],
    "reader_reception": {},
    "thoth_url": "https://chooser.crossref.org/?doi=10.11116%2F9789461664518",
    "public_discourse": {
      "news": [],
      "stackexchange": []
    },
    "social_mentions": {
      "wikipedia": [],
      "bluesky": [],
      "hypothesis": [],
      "reddit": [],
      "last_updated": "2026-04-16T09:15:04.407200+00:00",
      "substack": []
    },
    "risk_layer": {
      "is_retracted": false,
      "expression_of_concern": false,
      "pubpeer_threads": 0,
      "pubpeer_url": null,
      "corrections": []
    },
    "web_mentions": [],
    "news_coverage": {
      "total": 0,
      "articles": [],
      "top_domains": [],
      "top_countries": [],
      "source": "serpapi_google_news",
      "query": "\"Plutarch\u2019s Cosmological Ethics\" demulder"
    }
  },
  "roles": [
    {
      "id": "commercial_linkage",
      "label": "Commercial linkage",
      "strength": 0.9,
      "evidence": {
        "amazon": true,
        "goodreads": true
      }
    },
    {
      "id": "policy_sustainability",
      "label": "Sustainability & Policy relevance",
      "strength": 0.55,
      "evidence": {
        "sdg_count": 1
      }
    },
    {
      "id": "scholarly_uptake",
      "label": "Scholarly uptake",
      "strength": 0.45,
      "evidence": {
        "citations": 1
      }
    }
  ],
  "claims": [],
  "impact": {
    "citations": [
      {
        "openalex_id": "https://openalex.org/W4406219943",
        "doi": "10.14746/pea.2024.1.14",
        "url": "https://doi.org/10.14746/pea.2024.1.14",
        "title": "A Defense of \u201cAuthor\u2019s Mouthpiece\u201d",
        "year": 2024,
        "venue": "Peitho Examina Antiqua",
        "type": "article",
        "concepts": [
          "Mouthpiece",
          "Aeronautics",
          "Psychology"
        ],
        "countries": [],
        "authors": [
          "David J. Murphy|||https://openalex.org/A5112426257"
        ],
        "cited_by_count": 0
      }
    ],
    "scite": {
      "total": 0,
      "supporting": 0,
      "mentioning": 0,
      "contradicting": 0,
      "last_updated": null,
      "source_url": "https://scite.ai/reports/10.11116/9789461664518"
    },
    "events": {
      "total": 0,
      "events": []
    },
    "downloads": {
      "provider": "operas_metrics",
      "work_uri": "info:doi:10.11116/9789461664518",
      "totals": {
        "downloads": 1492
      },
      "by_source": [
        {
          "measure_uri": "https://metrics.operas-eu.org/oapen/downloads/v1",
          "label": "[{'locale_code': 'en_GB', 'locale_name': 'English - United Kingdom', 'description': ''}]",
          "source": "OAPEN",
          "type": "downloads",
          "value": 1492
        }
      ],
      "by_month": [
        {
          "month": "01",
          "measure_uri": "https://metrics.operas-eu.org/oapen/downloads/v1",
          "source": "OAPEN",
          "type": "downloads",
          "value": 108
        },
        {
          "month": "02",
          "measure_uri": "https://metrics.operas-eu.org/oapen/downloads/v1",
          "source": "OAPEN",
          "type": "downloads",
          "value": 136
        },
        {
          "month": "03",
          "measure_uri": "https://metrics.operas-eu.org/oapen/downloads/v1",
          "source": "OAPEN",
          "type": "downloads",
          "value": 211
        },
        {
          "month": "04",
          "measure_uri": "https://metrics.operas-eu.org/oapen/downloads/v1",
          "source": "OAPEN",
          "type": "downloads",
          "value": 191
        },
        {
          "month": "05",
          "measure_uri": "https://metrics.operas-eu.org/oapen/downloads/v1",
          "source": "OAPEN",
          "type": "downloads",
          "value": 122
        },
        {
          "month": "06",
          "measure_uri": "https://metrics.operas-eu.org/oapen/downloads/v1",
          "source": "OAPEN",
          "type": "downloads",
          "value": 103
        },
        {
          "month": "07",
          "measure_uri": "https://metrics.operas-eu.org/oapen/downloads/v1",
          "source": "OAPEN",
          "type": "downloads",
          "value": 124
        },
        {
          "month": "08",
          "measure_uri": "https://metrics.operas-eu.org/oapen/downloads/v1",
          "source": "OAPEN",
          "type": "downloads",
          "value": 97
        },
        {
          "month": "09",
          "measure_uri": "https://metrics.operas-eu.org/oapen/downloads/v1",
          "source": "OAPEN",
          "type": "downloads",
          "value": 68
        },
        {
          "month": "10",
          "measure_uri": "https://metrics.operas-eu.org/oapen/downloads/v1",
          "source": "OAPEN",
          "type": "downloads",
          "value": 106
        },
        {
          "month": "11",
          "measure_uri": "https://metrics.operas-eu.org/oapen/downloads/v1",
          "source": "OAPEN",
          "type": "downloads",
          "value": 127
        },
        {
          "month": "12",
          "measure_uri": "https://metrics.operas-eu.org/oapen/downloads/v1",
          "source": "OAPEN",
          "type": "downloads",
          "value": 99
        }
      ],
      "raw": {
        "totals_url": "https://metrics-api.operas-eu.org/events?aggregation=measure_uri&filter=work_uri%3Ainfo%3Adoi%3A10.11116%2F9789461664518",
        "monthly_url": "https://metrics-api.operas-eu.org/events?aggregation=month%2Cmeasure_uri&filter=work_uri%3Ainfo%3Adoi%3A10.11116%2F9789461664518",
        "monthly_included": true
      }
    }
  },
  "oer_listings": [],
  "oapen": {},
  "cover_image_url": null,
  "author_orcids": {},
  "narrative": "<h3 class=\"story-subheading\">Short impact summary</h3>\n<p class=\"story-text\">Published in 2022 by Leuven University Press, \"Plutarch\u2019s Cosmological Ethics\" has yet to gain measurable traction within academic discourse, evidenced by its current citation count of zero. Despite this, the work's engagement with philosophical themes surrounding ethics and cosmology continues to present potential value for scholars in the humanities.</p>\n<h3 class=\"story-subheading\">Full narrative</h3>\n<p class=\"story-text\">Although \"Plutarch\u2019s Cosmological Ethics\" has not yet attracted citations or community discussions on platforms such as Wikipedia or Reddit, its publication marks a noteworthy contribution to the field of philosophical ethics, particularly in relation to Plutarch's work. The absence of current attention metrics suggests that the book is still in the early stages of academic uptake, which may change as scholars increasingly explore interdisciplinary approaches within ethical study.</p>\n<p class=\"story-text\">The lack of recorded community engagement may indicate that scholars have not yet fully recognized or disseminated the themes presented within this work. Nonetheless, as academic trends evolve, the philosophical inquiries posed by Plutarch could resonate with current discourses around ethics in relation to cosmology, potentially paving the way for future discussions and publications.</p>\n<p class=\"story-text\">Despite its limited immediate impact, the book\u2019s classification under commercial linkage, supported by its availability on platforms like Amazon and Goodreads, highlights the potential for broader public engagement. As interest in Plutarch and his philosophical contributions continues to surface in academia, this work could serve as a critical resource for understanding cosmological ethics.</p>\n<p class=\"story-text\">In summary, while \"Plutarch\u2019s Cosmological Ethics\" currently lacks measurable engagement indicators, it resides in a potentially rich area for exploration. Its future impact may depend on the evolving discourse in humanities scholarship, particularly as scholars draw connections between historical philosophical texts and contemporary ethical discussions.</p>",
  "events": {},
  "scite": {},
  "story_type": "BookStory"
}